Workbook

Sheet Inputs
A1: Marginal Analysis — Model Inputs
A3: Name | B3: Value | C3: Unit | D3: Source
A4: Total Bed Capacity | B4: 64 | C4: beds | D4: Perfect Competition Case
A5: Season Length | B5: 36 | C5: weeks | D5: Perfect Competition Case
A6: Fixed Costs | B6: 20000 | C6: dollars/season | D6: Perfect Competition Case
A7: Farmer Field Hours | B7: 720 | C7: hours/season | D7: Perfect Competition Case
A8: Farmer Labor Rate | B8: 34.72 | C8: dollars/hour | D8: Perfect Competition Case
A9: Maximum Temporary Workers | B9: 4 | C9: workers | D9: Perfect Competition Case
A10: Temporary Worker Hours | B10: 1440 | C10: hours/worker/season | D10: Perfect Competition Case
A11: Temporary Labor Rate | B11: 17.36 | C11: dollars/hour | D11: Perfect Competition Case
A13: Tomato
A14: Tomato Bed Limit | B14: 20 | C14: beds | D14: Perfect Competition Case
A15: Tomato Revenue per Bed | B15: 8800 | C15: dollars/bed/season | D15: Perfect Competition Case
A16: Tomato Base Labor | B16: 2.5 | C16: hours/week/bed | D16: Perfect Competition Case
A17: Tomato Fertilizer Cost | B17: 880 | C17: dollars/bed/season | D17: Perfect Competition Case
A18: Tomato Diminishing-Returns Rate | B18: 0.1 | C18: per additional bed | D18: Perfect Competition Case
A20: Carrot
A21: Carrot Bed Limit | B21: 20 | C21: beds | D21: Perfect Competition Case
A22: Carrot Revenue per Bed | B22: 2094 | C22: dollars/bed/season | D22: Perfect Competition Case
A23: Carrot Base Labor | B23: 0.833 | C23: hours/week/bed | D23: Perfect Competition Case
A24: Carrot Fertilizer Cost | B24: 440 | C24: dollars/bed/season | D24: Perfect Competition Case
A25: Carrot Diminishing-Returns Rate | B25: 0.025 | C25: per additional bed | D25: Perfect Competition Case
A27: Mesclun
A28: Mesclun Bed Limit | B28: 30 | C28: beds | D28: Perfect Competition Case
A29: Mesclun Revenue per Bed | B29: 2700 | C29: dollars/bed/season | D29: Perfect Competition Case
A30: Mesclun Base Labor | B30: 1.25 | C30: hours/week/bed | D30: Perfect Competition Case
A31: Mesclun Fertilizer Cost | B31: 880 | C31: dollars/bed/season | D31: Perfect Competition Case
A32: Mesclun Diminishing-Returns Rate | B32: 0.0125 | C32: per additional bed | D32: Perfect Competition Case
A34: Maximum Possible Farm Labor Capacity | B34: =B7+B9*B10 -> 6480 | C34: hours/season | D34: Derived: Farmer Field Hours + (Max Temporary Workers × Temporary Worker Hours)
A36: Note: Revenue per Bed and Fertilizer Cost per Bed are full-season amounts and are not multiplied by Season Length. Season Length is used only to convert weekly base labor requirements into seasonal labor requirements.

Sheet Optimization
A1: Optimization — Decision Variables & Solver Setup
A3: SOLVER SETUP (run in Excel — Data > Solver): Set Objective: this sheet's Season Profit cell (maximize). By Changing Variable Cells: B7:B9 (Tomato/Carrot/Mesclun Beds below). Constraints: B7:B9 = integer; B7:B9 >= 0; B7 <= Tomato Bed Limit; B8 <= Carrot Bed Limit; B9 <= Mesclun Bed Limit; Total Beds Used <= Total Bed Capacity (64); Total Labor Required <= Total Labor Capacity; Total Labor Required <= Maximum Possible Farm Labor Capacity (6,480 hrs); Temporary Workers Needed <= 4. Solving Method: GRG Nonlinear. Run from at least two starting points — 0/0/0 and 20/0/0 — and confirm both converge to the same solution; if they differ, document it as an audit finding rather than silently picking one. NOTE: Solver is an interactive Excel add-in and cannot be operated by this file-generation process — see the Notes tab for how the decision-variable cells below were pre-populated and what you still need to verify yourself.
A6: Crop | B6: Beds (Decision Variable) | C6: Bed Limit | D6: Within Limit?
A7: Tomato | B7: 10 | C7: =Tom_Limit -> 20 | D7: =AND(B7>=0,B7<=C7) -> 1
A8: Carrot | B8: 20 | C8: =Car_Limit -> 20 | D8: =AND(B8>=0,B8<=C8) -> 1
A9: Mesclun | B9: 30 | C9: =Mes_Limit -> 30 | D9: =AND(B9>=0,B9<=C9) -> 1
A10: Total Beds Used | B10: =SUM(B7:B9) -> 60 | C10: =TotalBeds -> 64 | D10: =B10<=C10 -> 1
A12: Season Profit (Objective — Maximize) | B12: =SeasonProfit -> 42775.155
A14: Decision-variable cells (B7:B9) are pre-populated with the profit-maximizing whole-bed combination identified by exhaustive verification of every feasible integer combination (see Notes tab). Run Solver in Excel as described above to confirm this result yourself, as the specification requires.
A16: Solver Constraint Helper Cells (same-sheet links, for Excel Solver only)
A17: Total Labor Required (hrs) | B17: =TotalLaborRequired -> 5276.8228
A18: Total Labor Capacity (hrs) | B18: =TotalLaborCapacity -> 6480
A19: Maximum Farm Labor Capacity (hrs) | B19: =MaxLaborCapacity -> 6480
A20: Temporary Workers Needed | B20: =TempWorkersNeeded -> 4
A21: Maximum Temporary Workers | B21: =MaxTempWorkers -> 4

Sheet Cost Structure
A1: Cost Structure — Farm-Level Calculations
A3: Crop Mix (from Optimization)
A4: Tomato Beds | B4: =TomatoBeds -> 10
A5: Carrot Beds | B5: =CarrotBeds -> 20
A6: Mesclun Beds | B6: =MesclunBeds -> 30
A7: Total Beds Used | B7: =TotalBedsUsed -> 60
A9: Labor
A10: Tomato Labor Hours | B10: =IF(TomatoBeds=0,0,TomatoBeds*Tom_BaseLabor*SeasonLength*(1+Tom_DR)^TomatoBeds) -> 2334.3682
A11: Carrot Labor Hours | B11: =IF(CarrotBeds=0,0,CarrotBeds*Car_BaseLabor*SeasonLength*(1+Car_DR)^CarrotBeds) -> 982.7766
A12: Mesclun Labor Hours | B12: =IF(MesclunBeds=0,0,MesclunBeds*Mes_BaseLabor*SeasonLength*(1+Mes_DR)^MesclunBeds) -> 1959.678
A13: Total Labor Required | B13: =TomatoLaborHours+CarrotLaborHours+MesclunLaborHours -> 5276.8228
A14: Farmer Hours Used | B14: =MIN(TotalLaborRequired,FarmerHours) -> 720
A15: Temporary Labor Hours Needed | B15: =MAX(TotalLaborRequired-FarmerHours,0) -> 4556.8228
A16: Temporary Workers Needed | B16: =IF(TempLaborHoursNeeded=0,0,MIN(MaxTempWorkers,ROUNDUP(TempLaborHoursNeeded/TempWorkerHours,0))) -> 4
A17: Total Labor Capacity | B17: =FarmerHours+TempWorkersNeeded*TempWorkerHours -> 6480
A18: Unused Labor Capacity | B18: =TotalLaborCapacity-TotalLaborRequired -> 1203.1772
A20: Costs
A21: Farmer Labor Cost | B21: =FarmerHoursUsed*FarmerRate -> 24998.4
A22: Temporary Labor Cost | B22: =TempLaborHoursNeeded*TempRate -> 79106.445
A23: Total Labor Cost | B23: =FarmerLaborCost+TempLaborCost -> 104104.84
A24: Blended Labor Rate | B24: =IF(TotalLaborRequired=0,0,TotalLaborCost/TotalLaborRequired) -> 19.728698
A25: Tomato Fertilizer Cost | B25: =TomatoBeds*Tom_Fert -> 8800
A26: Carrot Fertilizer Cost | B26: =CarrotBeds*Car_Fert -> 8800
A27: Mesclun Fertilizer Cost | B27: =MesclunBeds*Mes_Fert -> 26400
A28: Total Fertilizer Cost | B28: =TomatoFertilizerCost+CarrotFertilizerCost+MesclunFertilizerCost -> 44000
A29: Fixed Costs | B29: =FixedCosts -> 20000
A30: Total Cost | B30: =FixedCosts+TotalFertilizerCost+TotalLaborCost -> 168104.84
A32: Revenue
A33: Tomato Revenue | B33: =TomatoBeds*Tom_Rev -> 88000
A34: Carrot Revenue | B34: =CarrotBeds*Car_Rev -> 41880
A35: Mesclun Revenue | B35: =MesclunBeds*Mes_Rev -> 81000
A36: Total Revenue | B36: =TomatoRevenue+CarrotRevenue+MesclunRevenue -> 210880
A38: Profit
A39: Season Profit | B39: =TotalRevenue-TotalCost -> 42775.155

Sheet Outputs
A1: Outputs — Summary Dashboard
A3: Optimal Crop Mix | C3: Labor
A4: Tomato Beds | B4: =TomatoBeds -> 10 | C4: Tomato Labor Hours | D4: ='Cost Structure'!B10 -> 2334.3682
A5: Carrot Beds | B5: =CarrotBeds -> 20 | C5: Carrot Labor Hours | D5: ='Cost Structure'!B11 -> 982.7766
A6: Mesclun Beds | B6: =MesclunBeds -> 30 | C6: Mesclun Labor Hours | D6: ='Cost Structure'!B12 -> 1959.678
A7: Total Beds Used | B7: =TotalBedsUsed -> 60 | C7: Total Labor Required | D7: =TotalLaborRequired -> 5276.8228
C8: Farmer Hours Used | D8: ='Cost Structure'!B14 -> 720
A9: Revenue | C9: Temporary Labor Hours Needed | D9: ='Cost Structure'!B15 -> 4556.8228
A10: Tomato Revenue | B10: ='Cost Structure'!B33 -> 88000 | C10: Temporary Workers Needed | D10: =TempWorkersNeeded -> 4
A11: Carrot Revenue | B11: ='Cost Structure'!B34 -> 41880 | C11: Total Labor Capacity | D11: =TotalLaborCapacity -> 6480
A12: Mesclun Revenue | B12: ='Cost Structure'!B35 -> 81000 | C12: Unused Labor Capacity | D12: ='Cost Structure'!B18 -> 1203.1772
A13: Total Revenue | B13: ='Cost Structure'!B36 -> 210880
C14: Costs
A15: Profit | C15: Tomato Fertilizer Cost | D15: ='Cost Structure'!B25 -> 8800
A16: Season Profit | B16: =SeasonProfit -> 42775.155 | C16: Carrot Fertilizer Cost | D16: ='Cost Structure'!B26 -> 8800
C17: Mesclun Fertilizer Cost | D17: ='Cost Structure'!B27 -> 26400
C18: Total Fertilizer Cost | D18: ='Cost Structure'!B28 -> 44000
C19: Farmer Labor Cost | D19: ='Cost Structure'!B21 -> 24998.4
C20: Temporary Labor Cost | D20: ='Cost Structure'!B22 -> 79106.445
C21: Total Labor Cost | D21: ='Cost Structure'!B23 -> 104104.84
C22: Blended Labor Rate | D22: ='Cost Structure'!B24 -> 19.728698
C23: Fixed Costs | D23: ='Cost Structure'!B29 -> 20000
C24: Total Farm Cost | D24: ='Cost Structure'!B30 -> 168104.84

Sheet MC - Tomato
A1: Standalone Marginal-Cost Schedule — Tomato
A2: Evaluates Tomato independently, as if it were the farm's only crop, from q = 0 through the tomato bed limit (20 beds). Fixed Costs ($20,000) are included in Total Cost at every quantity, including q = 0, and cancel out when Marginal Cost is calculated. Labor-infeasible quantities (Temp Workers Needed > 4, or Labor Hours > the 6,480-hour maximum farm labor capacity) are calculated and shown, not removed — see the Labor Feasible? column.
A5: Beds (q) | B5: Labor Hours | C5: Farmer Hours Used | D5: Temp Hours Needed | E5: Temp Workers Needed | F5: Labor Feasible? | G5: Farmer Labor Cost | H5: Temp Labor Cost | I5: Fertilizer Cost | J5: Total Labor Cost | K5: Total Cost (incl. Fixed) | L5: Marginal Cost | M5: Price (Revenue/Bed) | N5: MC <= Price? | O5: |Price - MC|
A6: 0 | B6: =IF($A6=0,0,$A6*Tom_BaseLabor*SeasonLength*(1+Tom_DR)^$A6) -> 0 | C6: =MIN(B6,FarmerHours) -> 0 | D6: =MAX(B6-FarmerHours,0) -> 0 | E6: =IF(D6=0,0,ROUNDUP(D6/TempWorkerHours,0)) -> 0 | F6: =AND(B6<=MaxLaborCapacity,E6<=MaxTempWorkers) -> TRUE | G6: =C6*FarmerRate -> 0 | H6: =D6*TempRate -> 0 | I6: =$A6*Tom_Fert -> 0 | J6: =G6+H6 -> 0 | K6: =FixedCosts+I6+J6 -> 20000 | M6: =Tom_Rev -> 8800
A7: 1 | B7: =IF($A7=0,0,$A7*Tom_BaseLabor*SeasonLength*(1+Tom_DR)^$A7) -> 99 | C7: =MIN(B7,FarmerHours) -> 99 | D7: =MAX(B7-FarmerHours,0) -> 0 | E7: =IF(D7=0,0,ROUNDUP(D7/TempWorkerHours,0)) -> 0 | F7: =AND(B7<=MaxLaborCapacity,E7<=MaxTempWorkers) -> TRUE | G7: =C7*FarmerRate -> 3437.28 | H7: =D7*TempRate -> 0 | I7: =$A7*Tom_Fert -> 880 | J7: =G7+H7 -> 3437.28 | K7: =FixedCosts+I7+J7 -> 24317.28 | L7: =K7-K6 -> 4317.28 | M7: =Tom_Rev -> 8800 | N7: =L7<=M7 -> TRUE | O7: =ABS(M7-L7) -> 4482.72
A8: 2 | B8: =IF($A8=0,0,$A8*Tom_BaseLabor*SeasonLength*(1+Tom_DR)^$A8) -> 217.8 | C8: =MIN(B8,FarmerHours) -> 217.8 | D8: =MAX(B8-FarmerHours,0) -> 0 | E8: =IF(D8=0,0,ROUNDUP(D8/TempWorkerHours,0)) -> 0 | F8: =AND(B8<=MaxLaborCapacity,E8<=MaxTempWorkers) -> TRUE | G8: =C8*FarmerRate -> 7562.016 | H8: =D8*TempRate -> 0 | I8: =$A8*Tom_Fert -> 1760 | J8: =G8+H8 -> 7562.016 | K8: =FixedCosts+I8+J8 -> 29322.016 | L8: =K8-K7 -> 5004.736 | M8: =Tom_Rev -> 8800 | N8: =L8<=M8 -> TRUE | O8: =ABS(M8-L8) -> 3795.264
A9: 3 | B9: =IF($A9=0,0,$A9*Tom_BaseLabor*SeasonLength*(1+Tom_DR)^$A9) -> 359.37 | C9: =MIN(B9,FarmerHours) -> 359.37 | D9: =MAX(B9-FarmerHours,0) -> 0 | E9: =IF(D9=0,0,ROUNDUP(D9/TempWorkerHours,0)) -> 0 | F9: =AND(B9<=MaxLaborCapacity,E9<=MaxTempWorkers) -> TRUE | G9: =C9*FarmerRate -> 12477.326 | H9: =D9*TempRate -> 0 | I9: =$A9*Tom_Fert -> 2640 | J9: =G9+H9 -> 12477.326 | K9: =FixedCosts+I9+J9 -> 35117.326 | L9: =K9-K8 -> 5795.3104 | M9: =Tom_Rev -> 8800 | N9: =L9<=M9 -> TRUE | O9: =ABS(M9-L9) -> 3004.6896
A10: 4 | B10: =IF($A10=0,0,$A10*Tom_BaseLabor*SeasonLength*(1+Tom_DR)^$A10) -> 527.076 | C10: =MIN(B10,FarmerHours) -> 527.076 | D10: =MAX(B10-FarmerHours,0) -> 0 | E10: =IF(D10=0,0,ROUNDUP(D10/TempWorkerHours,0)) -> 0 | F10: =AND(B10<=MaxLaborCapacity,E10<=MaxTempWorkers) -> TRUE | G10: =C10*FarmerRate -> 18300.079 | H10: =D10*TempRate -> 0 | I10: =$A10*Tom_Fert -> 3520 | J10: =G10+H10 -> 18300.079 | K10: =FixedCosts+I10+J10 -> 41820.079 | L10: =K10-K9 -> 6702.7523 | M10: =Tom_Rev -> 8800 | N10: =L10<=M10 -> TRUE | O10: =ABS(M10-L10) -> 2097.2477
A11: 5 | B11: =IF($A11=0,0,$A11*Tom_BaseLabor*SeasonLength*(1+Tom_DR)^$A11) -> 724.7295 | C11: =MIN(B11,FarmerHours) -> 720 | D11: =MAX(B11-FarmerHours,0) -> 4.7295 | E11: =IF(D11=0,0,ROUNDUP(D11/TempWorkerHours,0)) -> 1 | F11: =AND(B11<=MaxLaborCapacity,E11<=MaxTempWorkers) -> TRUE | G11: =C11*FarmerRate -> 24998.4 | H11: =D11*TempRate -> 82.10412 | I11: =$A11*Tom_Fert -> 4400 | J11: =G11+H11 -> 25080.504 | K11: =FixedCosts+I11+J11 -> 49480.504 | L11: =K11-K10 -> 7660.4254 | M11: =Tom_Rev -> 8800 | N11: =L11<=M11 -> TRUE | O11: =ABS(M11-L11) -> 1139.5746
A12: 6 | B12: =IF($A12=0,0,$A12*Tom_BaseLabor*SeasonLength*(1+Tom_DR)^$A12) -> 956.64294 | C12: =MIN(B12,FarmerHours) -> 720 | D12: =MAX(B12-FarmerHours,0) -> 236.64294 | E12: =IF(D12=0,0,ROUNDUP(D12/TempWorkerHours,0)) -> 1 | F12: =AND(B12<=MaxLaborCapacity,E12<=MaxTempWorkers) -> TRUE | G12: =C12*FarmerRate -> 24998.4 | H12: =D12*TempRate -> 4108.1214 | I12: =$A12*Tom_Fert -> 5280 | J12: =G12+H12 -> 29106.521 | K12: =FixedCosts+I12+J12 -> 54386.521 | L12: =K12-K11 -> 4906.0173 | M12: =Tom_Rev -> 8800 | N12: =L12<=M12 -> TRUE | O12: =ABS(M12-L12) -> 3893.9827
A13: 7 | B13: =IF($A13=0,0,$A13*Tom_BaseLabor*SeasonLength*(1+Tom_DR)^$A13) -> 1227.6918 | C13: =MIN(B13,FarmerHours) -> 720 | D13: =MAX(B13-FarmerHours,0) -> 507.69177 | E13: =IF(D13=0,0,ROUNDUP(D13/TempWorkerHours,0)) -> 1 | F13: =AND(B13<=MaxLaborCapacity,E13<=MaxTempWorkers) -> TRUE | G13: =C13*FarmerRate -> 24998.4 | H13: =D13*TempRate -> 8813.5292 | I13: =$A13*Tom_Fert -> 6160 | J13: =G13+H13 -> 33811.929 | K13: =FixedCosts+I13+J13 -> 59971.929 | L13: =K13-K12 -> 5585.4077 | M13: =Tom_Rev -> 8800 | N13: =L13<=M13 -> TRUE | O13: =ABS(M13-L13) -> 3214.5923
A14: 8 | B14: =IF($A14=0,0,$A14*Tom_BaseLabor*SeasonLength*(1+Tom_DR)^$A14) -> 1543.3839 | C14: =MIN(B14,FarmerHours) -> 720 | D14: =MAX(B14-FarmerHours,0) -> 823.38394 | E14: =IF(D14=0,0,ROUNDUP(D14/TempWorkerHours,0)) -> 1 | F14: =AND(B14<=MaxLaborCapacity,E14<=MaxTempWorkers) -> TRUE | G14: =C14*FarmerRate -> 24998.4 | H14: =D14*TempRate -> 14293.945 | I14: =$A14*Tom_Fert -> 7040 | J14: =G14+H14 -> 39292.345 | K14: =FixedCosts+I14+J14 -> 66332.345 | L14: =K14-K13 -> 6360.4161 | M14: =Tom_Rev -> 8800 | N14: =L14<=M14 -> TRUE | O14: =ABS(M14-L14) -> 2439.5839
A15: 9 | B15: =IF($A15=0,0,$A15*Tom_BaseLabor*SeasonLength*(1+Tom_DR)^$A15) -> 1909.9376 | C15: =MIN(B15,FarmerHours) -> 720 | D15: =MAX(B15-FarmerHours,0) -> 1189.9376 | E15: =IF(D15=0,0,ROUNDUP(D15/TempWorkerHours,0)) -> 1 | F15: =AND(B15<=MaxLaborCapacity,E15<=MaxTempWorkers) -> TRUE | G15: =C15*FarmerRate -> 24998.4 | H15: =D15*TempRate -> 20657.317 | I15: =$A15*Tom_Fert -> 7920 | J15: =G15+H15 -> 45655.717 | K15: =FixedCosts+I15+J15 -> 73575.717 | L15: =K15-K14 -> 7243.372 | M15: =Tom_Rev -> 8800 | N15: =L15<=M15 -> TRUE | O15: =ABS(M15-L15) -> 1556.628
A16: 10 | B16: =IF($A16=0,0,$A16*Tom_BaseLabor*SeasonLength*(1+Tom_DR)^$A16) -> 2334.3682 | C16: =MIN(B16,FarmerHours) -> 720 | D16: =MAX(B16-FarmerHours,0) -> 1614.3682 | E16: =IF(D16=0,0,ROUNDUP(D16/TempWorkerHours,0)) -> 2 | F16: =AND(B16<=MaxLaborCapacity,E16<=MaxTempWorkers) -> TRUE | G16: =C16*FarmerRate -> 24998.4 | H16: =D16*TempRate -> 28025.432 | I16: =$A16*Tom_Fert -> 8800 | J16: =G16+H16 -> 53023.832 | K16: =FixedCosts+I16+J16 -> 81823.832 | L16: =K16-K15 -> 8248.1149 | M16: =Tom_Rev -> 8800 | N16: =L16<=M16 -> TRUE | O16: =ABS(M16-L16) -> 551.88506
A17: 11 | B17: =IF($A17=0,0,$A17*Tom_BaseLabor*SeasonLength*(1+Tom_DR)^$A17) -> 2824.5855 | C17: =MIN(B17,FarmerHours) -> 720 | D17: =MAX(B17-FarmerHours,0) -> 2104.5855 | E17: =IF(D17=0,0,ROUNDUP(D17/TempWorkerHours,0)) -> 2 | F17: =AND(B17<=MaxLaborCapacity,E17<=MaxTempWorkers) -> TRUE | G17: =C17*FarmerRate -> 24998.4 | H17: =D17*TempRate -> 36535.605 | I17: =$A17*Tom_Fert -> 9680 | J17: =G17+H17 -> 61534.005 | K17: =FixedCosts+I17+J17 -> 91214.005 | L17: =K17-K16 -> 9390.1728 | M17: =Tom_Rev -> 8800 | N17: =L17<=M17 -> FALSE | O17: =ABS(M17-L17) -> 590.17276
A18: 12 | B18: =IF($A18=0,0,$A18*Tom_BaseLabor*SeasonLength*(1+Tom_DR)^$A18) -> 3389.5026 | C18: =MIN(B18,FarmerHours) -> 720 | D18: =MAX(B18-FarmerHours,0) -> 2669.5026 | E18: =IF(D18=0,0,ROUNDUP(D18/TempWorkerHours,0)) -> 2 | F18: =AND(B18<=MaxLaborCapacity,E18<=MaxTempWorkers) -> TRUE | G18: =C18*FarmerRate -> 24998.4 | H18: =D18*TempRate -> 46342.566 | I18: =$A18*Tom_Fert -> 10560 | J18: =G18+H18 -> 71340.966 | K18: =FixedCosts+I18+J18 -> 101900.97 | L18: =K18-K17 -> 10686.961 | M18: =Tom_Rev -> 8800 | N18: =L18<=M18 -> FALSE | O18: =ABS(M18-L18) -> 1886.961
... A26: 20 | B26: =IF($A26=0,0,$A26*Tom_BaseLabor*SeasonLength*(1+Tom_DR)^$A26) -> 12109.5 | C26: =MIN(B26,FarmerHours) -> 720 | D26: =MAX(B26-FarmerHours,0) -> 11389.5 | E26: =IF(D26=0,0,ROUNDUP(D26/TempWorkerHours,0)) -> 8 | F26: =AND(B26<=MaxLaborCapacity,E26<=MaxTempWorkers) -> FALSE | G26: =C26*FarmerRate -> 24998.4 | H26: =D26*TempRate -> 197721.72 | I26: =$A26*Tom_Fert -> 17600 | J26: =G26+H26 -> 222720.12 | K26: =FixedCosts+I26+J26 -> 260320.12 | L26: =K26-K25 -> 29546.489 | M26: =Tom_Rev -> 8800 | N26: =L26<=M26 -> FALSE | O26: =ABS(M26-L26) -> 20746.489

Sheet MC - Carrot
A1: Standalone Marginal-Cost Schedule — Carrot
A2: Evaluates Carrot independently, as if it were the farm's only crop, from q = 0 through the carrot bed limit (20 beds). Fixed Costs ($20,000) are included in Total Cost at every quantity, including q = 0, and cancel out when Marginal Cost is calculated. Labor-infeasible quantities (Temp Workers Needed > 4, or Labor Hours > the 6,480-hour maximum farm labor capacity) are calculated and shown, not removed — see the Labor Feasible? column.
A5: Beds (q) | B5: Labor Hours | C5: Farmer Hours Used | D5: Temp Hours Needed | E5: Temp Workers Needed | F5: Labor Feasible? | G5: Farmer Labor Cost | H5: Temp Labor Cost | I5: Fertilizer Cost | J5: Total Labor Cost | K5: Total Cost (incl. Fixed) | L5: Marginal Cost | M5: Price (Revenue/Bed) | N5: MC <= Price? | O5: |Price - MC|
A6: 0 | B6: =IF($A6=0,0,$A6*Car_BaseLabor*SeasonLength*(1+Car_DR)^$A6) -> 0 | C6: =MIN(B6,FarmerHours) -> 0 | D6: =MAX(B6-FarmerHours,0) -> 0 | E6: =IF(D6=0,0,ROUNDUP(D6/TempWorkerHours,0)) -> 0 | F6: =AND(B6<=MaxLaborCapacity,E6<=MaxTempWorkers) -> TRUE | G6: =C6*FarmerRate -> 0 | H6: =D6*TempRate -> 0 | I6: =$A6*Car_Fert -> 0 | J6: =G6+H6 -> 0 | K6: =FixedCosts+I6+J6 -> 20000 | M6: =Car_Rev -> 2094
A7: 1 | B7: =IF($A7=0,0,$A7*Car_BaseLabor*SeasonLength*(1+Car_DR)^$A7) -> 30.7377 | C7: =MIN(B7,FarmerHours) -> 30.7377 | D7: =MAX(B7-FarmerHours,0) -> 0 | E7: =IF(D7=0,0,ROUNDUP(D7/TempWorkerHours,0)) -> 0 | F7: =AND(B7<=MaxLaborCapacity,E7<=MaxTempWorkers) -> TRUE | G7: =C7*FarmerRate -> 1067.2129 | H7: =D7*TempRate -> 0 | I7: =$A7*Car_Fert -> 440 | J7: =G7+H7 -> 1067.2129 | K7: =FixedCosts+I7+J7 -> 21507.213 | L7: =K7-K6 -> 1507.2129 | M7: =Car_Rev -> 2094 | N7: =L7<=M7 -> TRUE | O7: =ABS(M7-L7) -> 586.78706
A8: 2 | B8: =IF($A8=0,0,$A8*Car_BaseLabor*SeasonLength*(1+Car_DR)^$A8) -> 63.012285 | C8: =MIN(B8,FarmerHours) -> 63.012285 | D8: =MAX(B8-FarmerHours,0) -> 0 | E8: =IF(D8=0,0,ROUNDUP(D8/TempWorkerHours,0)) -> 0 | F8: =AND(B8<=MaxLaborCapacity,E8<=MaxTempWorkers) -> TRUE | G8: =C8*FarmerRate -> 2187.7865 | H8: =D8*TempRate -> 0 | I8: =$A8*Car_Fert -> 880 | J8: =G8+H8 -> 2187.7865 | K8: =FixedCosts+I8+J8 -> 23067.787 | L8: =K8-K7 -> 1560.5736 | M8: =Car_Rev -> 2094 | N8: =L8<=M8 -> TRUE | O8: =ABS(M8-L8) -> 533.42641
A9: 3 | B9: =IF($A9=0,0,$A9*Car_BaseLabor*SeasonLength*(1+Car_DR)^$A9) -> 96.881388 | C9: =MIN(B9,FarmerHours) -> 96.881388 | D9: =MAX(B9-FarmerHours,0) -> 0 | E9: =IF(D9=0,0,ROUNDUP(D9/TempWorkerHours,0)) -> 0 | F9: =AND(B9<=MaxLaborCapacity,E9<=MaxTempWorkers) -> TRUE | G9: =C9*FarmerRate -> 3363.7218 | H9: =D9*TempRate -> 0 | I9: =$A9*Car_Fert -> 1320 | J9: =G9+H9 -> 3363.7218 | K9: =FixedCosts+I9+J9 -> 24683.722 | L9: =K9-K8 -> 1615.9353 | M9: =Car_Rev -> 2094 | N9: =L9<=M9 -> TRUE | O9: =ABS(M9-L9) -> 478.06474
A10: 4 | B10: =IF($A10=0,0,$A10*Car_BaseLabor*SeasonLength*(1+Car_DR)^$A10) -> 132.40456 | C10: =MIN(B10,FarmerHours) -> 132.40456 | D10: =MAX(B10-FarmerHours,0) -> 0 | E10: =IF(D10=0,0,ROUNDUP(D10/TempWorkerHours,0)) -> 0 | F10: =AND(B10<=MaxLaborCapacity,E10<=MaxTempWorkers) -> TRUE | G10: =C10*FarmerRate -> 4597.0865 | H10: =D10*TempRate -> 0 | I10: =$A10*Car_Fert -> 1760 | J10: =G10+H10 -> 4597.0865 | K10: =FixedCosts+I10+J10 -> 26357.086 | L10: =K10-K9 -> 1673.3647 | M10: =Car_Rev -> 2094 | N10: =L10<=M10 -> TRUE | O10: =ABS(M10-L10) -> 420.63534
A11: 5 | B11: =IF($A11=0,0,$A11*Car_BaseLabor*SeasonLength*(1+Car_DR)^$A11) -> 169.64335 | C11: =MIN(B11,FarmerHours) -> 169.64335 | D11: =MAX(B11-FarmerHours,0) -> 0 | E11: =IF(D11=0,0,ROUNDUP(D11/TempWorkerHours,0)) -> 0 | F11: =AND(B11<=MaxLaborCapacity,E11<=MaxTempWorkers) -> TRUE | G11: =C11*FarmerRate -> 5890.017 | H11: =D11*TempRate -> 0 | I11: =$A11*Car_Fert -> 2200 | J11: =G11+H11 -> 5890.017 | K11: =FixedCosts+I11+J11 -> 28090.017 | L11: =K11-K10 -> 1732.9306 | M11: =Car_Rev -> 2094 | N11: =L11<=M11 -> TRUE | O11: =ABS(M11-L11) -> 361.06943
A12: 6 | B12: =IF($A12=0,0,$A12*Car_BaseLabor*SeasonLength*(1+Car_DR)^$A12) -> 208.66132 | C12: =MIN(B12,FarmerHours) -> 208.66132 | D12: =MAX(B12-FarmerHours,0) -> 0 | E12: =IF(D12=0,0,ROUNDUP(D12/TempWorkerHours,0)) -> 0 | F12: =AND(B12<=MaxLaborCapacity,E12<=MaxTempWorkers) -> TRUE | G12: =C12*FarmerRate -> 7244.7209 | H12: =D12*TempRate -> 0 | I12: =$A12*Car_Fert -> 2640 | J12: =G12+H12 -> 7244.7209 | K12: =FixedCosts+I12+J12 -> 29884.721 | L12: =K12-K11 -> 1794.7039 | M12: =Car_Rev -> 2094 | N12: =L12<=M12 -> TRUE | O12: =ABS(M12-L12) -> 299.29608
A13: 7 | B13: =IF($A13=0,0,$A13*Car_BaseLabor*SeasonLength*(1+Car_DR)^$A13) -> 249.52416 | C13: =MIN(B13,FarmerHours) -> 249.52416 | D13: =MAX(B13-FarmerHours,0) -> 0 | E13: =IF(D13=0,0,ROUNDUP(D13/TempWorkerHours,0)) -> 0 | F13: =AND(B13<=MaxLaborCapacity,E13<=MaxTempWorkers) -> TRUE | G13: =C13*FarmerRate -> 8663.4788 | H13: =D13*TempRate -> 0 | I13: =$A13*Car_Fert -> 3080 | J13: =G13+H13 -> 8663.4788 | K13: =FixedCosts+I13+J13 -> 31743.479 | L13: =K13-K12 -> 1858.7579 | M13: =Car_Rev -> 2094 | N13: =L13<=M13 -> TRUE | O13: =ABS(M13-L13) -> 235.24215
A14: 8 | B14: =IF($A14=0,0,$A14*Car_BaseLabor*SeasonLength*(1+Car_DR)^$A14) -> 292.29973 | C14: =MIN(B14,FarmerHours) -> 292.29973 | D14: =MAX(B14-FarmerHours,0) -> 0 | E14: =IF(D14=0,0,ROUNDUP(D14/TempWorkerHours,0)) -> 0 | F14: =AND(B14<=MaxLaborCapacity,E14<=MaxTempWorkers) -> TRUE | G14: =C14*FarmerRate -> 10148.647 | H14: =D14*TempRate -> 0 | I14: =$A14*Car_Fert -> 3520 | J14: =G14+H14 -> 10148.647 | K14: =FixedCosts+I14+J14 -> 33668.647 | L14: =K14-K13 -> 1925.1678 | M14: =Car_Rev -> 2094 | N14: =L14<=M14 -> TRUE | O14: =ABS(M14-L14) -> 168.83221
A15: 9 | B15: =IF($A15=0,0,$A15*Car_BaseLabor*SeasonLength*(1+Car_DR)^$A15) -> 337.05812 | C15: =MIN(B15,FarmerHours) -> 337.05812 | D15: =MAX(B15-FarmerHours,0) -> 0 | E15: =IF(D15=0,0,ROUNDUP(D15/TempWorkerHours,0)) -> 0 | F15: =AND(B15<=MaxLaborCapacity,E15<=MaxTempWorkers) -> TRUE | G15: =C15*FarmerRate -> 11702.658 | H15: =D15*TempRate -> 0 | I15: =$A15*Car_Fert -> 3960 | J15: =G15+H15 -> 11702.658 | K15: =FixedCosts+I15+J15 -> 35662.658 | L15: =K15-K14 -> 1994.0115 | M15: =Car_Rev -> 2094 | N15: =L15<=M15 -> TRUE | O15: =ABS(M15-L15) -> 99.988492
A16: 10 | B16: =IF($A16=0,0,$A16*Car_BaseLabor*SeasonLength*(1+Car_DR)^$A16) -> 383.87175 | C16: =MIN(B16,FarmerHours) -> 383.87175 | D16: =MAX(B16-FarmerHours,0) -> 0 | E16: =IF(D16=0,0,ROUNDUP(D16/TempWorkerHours,0)) -> 0 | F16: =AND(B16<=MaxLaborCapacity,E16<=MaxTempWorkers) -> TRUE | G16: =C16*FarmerRate -> 13328.027 | H16: =D16*TempRate -> 0 | I16: =$A16*Car_Fert -> 4400 | J16: =G16+H16 -> 13328.027 | K16: =FixedCosts+I16+J16 -> 37728.027 | L16: =K16-K15 -> 2065.3692 | M16: =Car_Rev -> 2094 | N16: =L16<=M16 -> TRUE | O16: =ABS(M16-L16) -> 28.630821
A17: 11 | B17: =IF($A17=0,0,$A17*Car_BaseLabor*SeasonLength*(1+Car_DR)^$A17) -> 432.8154 | C17: =MIN(B17,FarmerHours) -> 432.8154 | D17: =MAX(B17-FarmerHours,0) -> 0 | E17: =IF(D17=0,0,ROUNDUP(D17/TempWorkerHours,0)) -> 0 | F17: =AND(B17<=MaxLaborCapacity,E17<=MaxTempWorkers) -> TRUE | G17: =C17*FarmerRate -> 15027.351 | H17: =D17*TempRate -> 0 | I17: =$A17*Car_Fert -> 4840 | J17: =G17+H17 -> 15027.351 | K17: =FixedCosts+I17+J17 -> 39867.351 | L17: =K17-K16 -> 2139.3235 | M17: =Car_Rev -> 2094 | N17: =L17<=M17 -> FALSE | O17: =ABS(M17-L17) -> 45.323477
A18: 12 | B18: =IF($A18=0,0,$A18*Car_BaseLabor*SeasonLength*(1+Car_DR)^$A18) -> 483.96631 | C18: =MIN(B18,FarmerHours) -> 483.96631 | D18: =MAX(B18-FarmerHours,0) -> 0 | E18: =IF(D18=0,0,ROUNDUP(D18/TempWorkerHours,0)) -> 0 | F18: =AND(B18<=MaxLaborCapacity,E18<=MaxTempWorkers) -> TRUE | G18: =C18*FarmerRate -> 16803.31 | H18: =D18*TempRate -> 0 | I18: =$A18*Car_Fert -> 5280 | J18: =G18+H18 -> 16803.31 | K18: =FixedCosts+I18+J18 -> 42083.31 | L18: =K18-K17 -> 2215.9596 | M18: =Car_Rev -> 2094 | N18: =L18<=M18 -> FALSE | O18: =ABS(M18-L18) -> 121.95963
... A26: 20 | B26: =IF($A26=0,0,$A26*Car_BaseLabor*SeasonLength*(1+Car_DR)^$A26) -> 982.7766 | C26: =MIN(B26,FarmerHours) -> 720 | D26: =MAX(B26-FarmerHours,0) -> 262.7766 | E26: =IF(D26=0,0,ROUNDUP(D26/TempWorkerHours,0)) -> 1 | F26: =AND(B26<=MaxLaborCapacity,E26<=MaxTempWorkers) -> TRUE | G26: =C26*FarmerRate -> 24998.4 | H26: =D26*TempRate -> 4561.8017 | I26: =$A26*Car_Fert -> 8800 | J26: =G26+H26 -> 29560.202 | K26: =FixedCosts+I26+J26 -> 58360.202 | L26: =K26-K25 -> 1688.366 | M26: =Car_Rev -> 2094 | N26: =L26<=M26 -> TRUE | O26: =ABS(M26-L26) -> 405.63402

Sheet MC - Mesclun
A1: Standalone Marginal-Cost Schedule — Mesclun
A2: Evaluates Mesclun independently, as if it were the farm's only crop, from q = 0 through the mesclun bed limit (30 beds). Fixed Costs ($20,000) are included in Total Cost at every quantity, including q = 0, and cancel out when Marginal Cost is calculated. Labor-infeasible quantities (Temp Workers Needed > 4, or Labor Hours > the 6,480-hour maximum farm labor capacity) are calculated and shown, not removed — see the Labor Feasible? column.
A5: Beds (q) | B5: Labor Hours | C5: Farmer Hours Used | D5: Temp Hours Needed | E5: Temp Workers Needed | F5: Labor Feasible? | G5: Farmer Labor Cost | H5: Temp Labor Cost | I5: Fertilizer Cost | J5: Total Labor Cost | K5: Total Cost (incl. Fixed) | L5: Marginal Cost | M5: Price (Revenue/Bed) | N5: MC <= Price? | O5: |Price - MC|
A6: 0 | B6: =IF($A6=0,0,$A6*Mes_BaseLabor*SeasonLength*(1+Mes_DR)^$A6) -> 0 | C6: =MIN(B6,FarmerHours) -> 0 | D6: =MAX(B6-FarmerHours,0) -> 0 | E6: =IF(D6=0,0,ROUNDUP(D6/TempWorkerHours,0)) -> 0 | F6: =AND(B6<=MaxLaborCapacity,E6<=MaxTempWorkers) -> TRUE | G6: =C6*FarmerRate -> 0 | H6: =D6*TempRate -> 0 | I6: =$A6*Mes_Fert -> 0 | J6: =G6+H6 -> 0 | K6: =FixedCosts+I6+J6 -> 20000 | M6: =Mes_Rev -> 2700
A7: 1 | B7: =IF($A7=0,0,$A7*Mes_BaseLabor*SeasonLength*(1+Mes_DR)^$A7) -> 45.5625 | C7: =MIN(B7,FarmerHours) -> 45.5625 | D7: =MAX(B7-FarmerHours,0) -> 0 | E7: =IF(D7=0,0,ROUNDUP(D7/TempWorkerHours,0)) -> 0 | F7: =AND(B7<=MaxLaborCapacity,E7<=MaxTempWorkers) -> TRUE | G7: =C7*FarmerRate -> 1581.93 | H7: =D7*TempRate -> 0 | I7: =$A7*Mes_Fert -> 880 | J7: =G7+H7 -> 1581.93 | K7: =FixedCosts+I7+J7 -> 22461.93 | L7: =K7-K6 -> 2461.93 | M7: =Mes_Rev -> 2700 | N7: =L7<=M7 -> TRUE | O7: =ABS(M7-L7) -> 238.07
A8: 2 | B8: =IF($A8=0,0,$A8*Mes_BaseLabor*SeasonLength*(1+Mes_DR)^$A8) -> 92.264062 | C8: =MIN(B8,FarmerHours) -> 92.264062 | D8: =MAX(B8-FarmerHours,0) -> 0 | E8: =IF(D8=0,0,ROUNDUP(D8/TempWorkerHours,0)) -> 0 | F8: =AND(B8<=MaxLaborCapacity,E8<=MaxTempWorkers) -> TRUE | G8: =C8*FarmerRate -> 3203.4082 | H8: =D8*TempRate -> 0 | I8: =$A8*Mes_Fert -> 1760 | J8: =G8+H8 -> 3203.4082 | K8: =FixedCosts+I8+J8 -> 24963.408 | L8: =K8-K7 -> 2501.4783 | M8: =Mes_Rev -> 2700 | N8: =L8<=M8 -> TRUE | O8: =ABS(M8-L8) -> 198.52175
A9: 3 | B9: =IF($A9=0,0,$A9*Mes_BaseLabor*SeasonLength*(1+Mes_DR)^$A9) -> 140.12604 | C9: =MIN(B9,FarmerHours) -> 140.12604 | D9: =MAX(B9-FarmerHours,0) -> 0 | E9: =IF(D9=0,0,ROUNDUP(D9/TempWorkerHours,0)) -> 0 | F9: =AND(B9<=MaxLaborCapacity,E9<=MaxTempWorkers) -> TRUE | G9: =C9*FarmerRate -> 4865.1763 | H9: =D9*TempRate -> 0 | I9: =$A9*Mes_Fert -> 2640 | J9: =G9+H9 -> 4865.1763 | K9: =FixedCosts+I9+J9 -> 27505.176 | L9: =K9-K8 -> 2541.768 | M9: =Mes_Rev -> 2700 | N9: =L9<=M9 -> TRUE | O9: =ABS(M9-L9) -> 158.23197
A10: 4 | B10: =IF($A10=0,0,$A10*Mes_BaseLabor*SeasonLength*(1+Mes_DR)^$A10) -> 189.17016 | C10: =MIN(B10,FarmerHours) -> 189.17016 | D10: =MAX(B10-FarmerHours,0) -> 0 | E10: =IF(D10=0,0,ROUNDUP(D10/TempWorkerHours,0)) -> 0 | F10: =AND(B10<=MaxLaborCapacity,E10<=MaxTempWorkers) -> TRUE | G10: =C10*FarmerRate -> 6567.988 | H10: =D10*TempRate -> 0 | I10: =$A10*Mes_Fert -> 3520 | J10: =G10+H10 -> 6567.988 | K10: =FixedCosts+I10+J10 -> 30087.988 | L10: =K10-K9 -> 2582.8117 | M10: =Mes_Rev -> 2700 | N10: =L10<=M10 -> TRUE | O10: =ABS(M10-L10) -> 117.1883
A11: 5 | B11: =IF($A11=0,0,$A11*Mes_BaseLabor*SeasonLength*(1+Mes_DR)^$A11) -> 239.41848 | C11: =MIN(B11,FarmerHours) -> 239.41848 | D11: =MAX(B11-FarmerHours,0) -> 0 | E11: =IF(D11=0,0,ROUNDUP(D11/TempWorkerHours,0)) -> 0 | F11: =AND(B11<=MaxLaborCapacity,E11<=MaxTempWorkers) -> TRUE | G11: =C11*FarmerRate -> 8312.6098 | H11: =D11*TempRate -> 0 | I11: =$A11*Mes_Fert -> 4400 | J11: =G11+H11 -> 8312.6098 | K11: =FixedCosts+I11+J11 -> 32712.61 | L11: =K11-K10 -> 2624.6218 | M11: =Mes_Rev -> 2700 | N11: =L11<=M11 -> TRUE | O11: =ABS(M11-L11) -> 75.378193
A12: 6 | B12: =IF($A12=0,0,$A12*Mes_BaseLabor*SeasonLength*(1+Mes_DR)^$A12) -> 290.89346 | C12: =MIN(B12,FarmerHours) -> 290.89346 | D12: =MAX(B12-FarmerHours,0) -> 0 | E12: =IF(D12=0,0,ROUNDUP(D12/TempWorkerHours,0)) -> 0 | F12: =AND(B12<=MaxLaborCapacity,E12<=MaxTempWorkers) -> TRUE | G12: =C12*FarmerRate -> 10099.821 | H12: =D12*TempRate -> 0 | I12: =$A12*Mes_Fert -> 5280 | J12: =G12+H12 -> 10099.821 | K12: =FixedCosts+I12+J12 -> 35379.821 | L12: =K12-K11 -> 2667.2111 | M12: =Mes_Rev -> 2700 | N12: =L12<=M12 -> TRUE | O12: =ABS(M12-L12) -> 32.788896
A13: 7 | B13: =IF($A13=0,0,$A13*Mes_BaseLabor*SeasonLength*(1+Mes_DR)^$A13) -> 343.6179 | C13: =MIN(B13,FarmerHours) -> 343.6179 | D13: =MAX(B13-FarmerHours,0) -> 0 | E13: =IF(D13=0,0,ROUNDUP(D13/TempWorkerHours,0)) -> 0 | F13: =AND(B13<=MaxLaborCapacity,E13<=MaxTempWorkers) -> TRUE | G13: =C13*FarmerRate -> 11930.413 | H13: =D13*TempRate -> 0 | I13: =$A13*Mes_Fert -> 6160 | J13: =G13+H13 -> 11930.413 | K13: =FixedCosts+I13+J13 -> 38090.413 | L13: =K13-K12 -> 2710.5925 | M13: =Mes_Rev -> 2700 | N13: =L13<=M13 -> FALSE | O13: =ABS(M13-L13) -> 10.592536
A14: 8 | B14: =IF($A14=0,0,$A14*Mes_BaseLabor*SeasonLength*(1+Mes_DR)^$A14) -> 397.615 | C14: =MIN(B14,FarmerHours) -> 397.615 | D14: =MAX(B14-FarmerHours,0) -> 0 | E14: =IF(D14=0,0,ROUNDUP(D14/TempWorkerHours,0)) -> 0 | F14: =AND(B14<=MaxLaborCapacity,E14<=MaxTempWorkers) -> TRUE | G14: =C14*FarmerRate -> 13805.193 | H14: =D14*TempRate -> 0 | I14: =$A14*Mes_Fert -> 7040 | J14: =G14+H14 -> 13805.193 | K14: =FixedCosts+I14+J14 -> 40845.193 | L14: =K14-K13 -> 2754.7793 | M14: =Mes_Rev -> 2700 | N14: =L14<=M14 -> FALSE | O14: =ABS(M14-L14) -> 54.779252
A15: 9 | B15: =IF($A15=0,0,$A15*Mes_BaseLabor*SeasonLength*(1+Mes_DR)^$A15) -> 452.90833 | C15: =MIN(B15,FarmerHours) -> 452.90833 | D15: =MAX(B15-FarmerHours,0) -> 0 | E15: =IF(D15=0,0,ROUNDUP(D15/TempWorkerHours,0)) -> 0 | F15: =AND(B15<=MaxLaborCapacity,E15<=MaxTempWorkers) -> TRUE | G15: =C15*FarmerRate -> 15724.977 | H15: =D15*TempRate -> 0 | I15: =$A15*Mes_Fert -> 7920 | J15: =G15+H15 -> 15724.977 | K15: =FixedCosts+I15+J15 -> 43644.977 | L15: =K15-K14 -> 2799.7846 | M15: =Mes_Rev -> 2700 | N15: =L15<=M15 -> FALSE | O15: =ABS(M15-L15) -> 99.784606
A16: 10 | B16: =IF($A16=0,0,$A16*Mes_BaseLabor*SeasonLength*(1+Mes_DR)^$A16) -> 509.52187 | C16: =MIN(B16,FarmerHours) -> 509.52187 | D16: =MAX(B16-FarmerHours,0) -> 0 | E16: =IF(D16=0,0,ROUNDUP(D16/TempWorkerHours,0)) -> 0 | F16: =AND(B16<=MaxLaborCapacity,E16<=MaxTempWorkers) -> TRUE | G16: =C16*FarmerRate -> 17690.599 | H16: =D16*TempRate -> 0 | I16: =$A16*Mes_Fert -> 8800 | J16: =G16+H16 -> 17690.599 | K16: =FixedCosts+I16+J16 -> 46490.599 | L16: =K16-K15 -> 2845.6222 | M16: =Mes_Rev -> 2700 | N16: =L16<=M16 -> FALSE | O16: =ABS(M16-L16) -> 145.62216
A17: 11 | B17: =IF($A17=0,0,$A17*Mes_BaseLabor*SeasonLength*(1+Mes_DR)^$A17) -> 567.47999 | C17: =MIN(B17,FarmerHours) -> 567.47999 | D17: =MAX(B17-FarmerHours,0) -> 0 | E17: =IF(D17=0,0,ROUNDUP(D17/TempWorkerHours,0)) -> 0 | F17: =AND(B17<=MaxLaborCapacity,E17<=MaxTempWorkers) -> TRUE | G17: =C17*FarmerRate -> 19702.905 | H17: =D17*TempRate -> 0 | I17: =$A17*Mes_Fert -> 9680 | J17: =G17+H17 -> 19702.905 | K17: =FixedCosts+I17+J17 -> 49382.905 | L17: =K17-K16 -> 2892.3057 | M17: =Mes_Rev -> 2700 | N17: =L17<=M17 -> FALSE | O17: =ABS(M17-L17) -> 192.30569
A18: 12 | B18: =IF($A18=0,0,$A18*Mes_BaseLabor*SeasonLength*(1+Mes_DR)^$A18) -> 626.80744 | C18: =MIN(B18,FarmerHours) -> 626.80744 | D18: =MAX(B18-FarmerHours,0) -> 0 | E18: =IF(D18=0,0,ROUNDUP(D18/TempWorkerHours,0)) -> 0 | F18: =AND(B18<=MaxLaborCapacity,E18<=MaxTempWorkers) -> TRUE | G18: =C18*FarmerRate -> 21762.754 | H18: =D18*TempRate -> 0 | I18: =$A18*Mes_Fert -> 10560 | J18: =G18+H18 -> 21762.754 | K18: =FixedCosts+I18+J18 -> 52322.754 | L18: =K18-K17 -> 2939.8492 | M18: =Mes_Rev -> 2700 | N18: =L18<=M18 -> FALSE | O18: =ABS(M18-L18) -> 239.84917
... A36: 30 | B36: =IF($A36=0,0,$A36*Mes_BaseLabor*SeasonLength*(1+Mes_DR)^$A36) -> 1959.678 | C36: =MIN(B36,FarmerHours) -> 720 | D36: =MAX(B36-FarmerHours,0) -> 1239.678 | E36: =IF(D36=0,0,ROUNDUP(D36/TempWorkerHours,0)) -> 1 | F36: =AND(B36<=MaxLaborCapacity,E36<=MaxTempWorkers) -> TRUE | G36: =C36*FarmerRate -> 24998.4 | H36: =D36*TempRate -> 21520.811 | I36: =$A36*Mes_Fert -> 26400 | J36: =G36+H36 -> 46519.211 | K36: =FixedCosts+I36+J36 -> 92919.211 | L36: =K36-K35 -> 2420.0005 | M36: =Mes_Rev -> 2700 | N36: =L36<=M36 -> TRUE | O36: =ABS(M36-L36) -> 279.99952

Sheet Checks
A1: Checks — Constraint Status
A2: All checks below must show PASS for the optimized crop mix on the Optimization tab to be a feasible solution.
A4: Constraint | B4: Status | C4: Detail
A5: Tomato Beds within crop limit (0-20) | B5: =AND(TomatoBeds=INT(TomatoBeds),TomatoBeds>=0,TomatoBeds<=Tom_Limit) -> TRUE | C5: Tomato Beds must be a nonnegative integer <= Tomato Bed Limit
A6: Carrot Beds within crop limit (0-20) | B6: =AND(CarrotBeds=INT(CarrotBeds),CarrotBeds>=0,CarrotBeds<=Car_Limit) -> TRUE | C6: Carrot Beds must be a nonnegative integer <= Carrot Bed Limit
A7: Mesclun Beds within crop limit (0-30) | B7: =AND(MesclunBeds=INT(MesclunBeds),MesclunBeds>=0,MesclunBeds<=Mes_Limit) -> TRUE | C7: Mesclun Beds must be a nonnegative integer <= Mesclun Bed Limit
A8: Total Beds Used within Total Bed Capacity (64) | B8: =TotalBedsUsed<=TotalBeds -> TRUE | C8: Sum of all crop beds must not exceed 64
A9: Total Labor Required within Total Labor Capacity | B9: =TotalLaborRequired<=TotalLaborCapacity -> TRUE | C9: Total Labor Required must not exceed farmer + temporary-worker labor capacity
A10: Total Labor Required within Maximum Farm Labor Capacity (6,480 hrs) | B10: =TotalLaborRequired<=MaxLaborCapacity -> TRUE | C10: Total Labor Required must not exceed the farm's maximum possible labor capacity
A11: Temporary Workers Needed within limit (<= 4) | B11: =TempWorkersNeeded<=MaxTempWorkers -> TRUE | C11: No more than 4 temporary workers are available
A13: All Checks Pass? | B13: =AND(B5,B6,B7,B8,B9,B10,B11) -> TRUE

Sheet Notes
A1: Notes & Audit Findings (build-time)
A3: 1. Solver could not be run by this build process.
A4: Excel's Solver add-in (and its GRG Nonlinear engine) is an interactive Excel feature and cannot be configured or executed by a file-generation script. The Optimization tab documents the full Solver setup (objective cell, changing cells, constraints, method) for you to run yourself in Excel. As a substitute check — not a replacement for actually running Solver — every feasible whole-bed combination of Tomato (0-20), Carrot (0-20), and Mesclun (0-30) beds satisfying all constraints (total beds <= 64, labor required <= labor capacity, labor required <= 6,480 hrs, temp workers <= 4) was evaluated exhaustively outside the workbook. The global optimum found this way is 10 Tomato / 20 Carrot / 30 Mesclun beds (60 total beds), matching the spec's published check figure exactly. The decision-variable cells on the Optimization tab are pre-populated with this result.
A6: 2. Please run Solver in Excel yourself to confirm.
A7: The spec requires running Solver from two starting points (0/0/0 and 20/0/0) and documenting any difference between the two as an audit finding. Because the exhaustive check above is a single global search (not two separate Solver runs), it cannot substitute for this step. Please run Solver from both starting points in Excel and confirm both converge to 10/20/30 as expected.
A9: 3. Small profit discrepancy vs. the published check figure.
A10: This workbook's formulas calculate Season Profit at 10/20/30 beds as $42,775.16. The spec's published check figure is "approximately $42,762" — a difference of about $13 (0.03%). The formulas were verified independently (hand recomputation and the Validation Rules checks below) and no error was found on this end; the small gap is most likely rounding in the spec author's own reference calculation. Flagging this for your manual audit rather than adjusting the model to force a match.
A12: 4. Farm Profit Lab cross-check not performed.
A13: The spec's Validation Rules ask that at least one intermediate marginal-cost result be cross-checked against the "Farm Profit Lab" during the audit. This build process has no access to that tool, so this step has not been done and is left for you to complete.
A15: 5. Validation Rules checked during the build.
A16: Tomato labor at q=1 = 99.00 hours (matches spec). Tomato labor at q=10 = 2,334.37 hours (matches spec's ~2,334.37). Standalone P (approx.) = MC crossing: Tomato at q=10, Carrot at q=10, Mesclun at q=6 — all match the spec's stated quantities, using "largest q where Marginal Cost <= Price" as the crossing rule (each schedule's MC keeps rising through this quantity in the normal labor-cost regime; MC can dip after farmer hours are exhausted because temporary labor, at $17.36/hr, is cheaper than farmer labor at $34.72/hr — this is a real effect of the labor-cost structure, not a formula error, and is visible directly in each MC schedule tab).
A18: 6. Recalculation.
A19: This workbook was recalculated with LibreOffice after being built so that every formula carries a cached value and no formula errors remain. Please still open it in Excel and confirm Solver reproduces the same result, per notes 1-2 above.
